.gitignore
MANIFEST.in
README.rst
VERSION.txt
pyproject.toml
sage_conf.py.in
setup.cfg
setup.py
tox.ini
bin/sage-env-config.in
sage_conf.egg-info/PKG-INFO
sage_conf.egg-info/SOURCES.txt
sage_conf.egg-info/dependency_links.txt
sage_conf.egg-info/top_level.txt
sage_root/.homebrew-build-env
sage_root/Makefile
sage_root/README.md
sage_root/VERSION.txt
sage_root/bootstrap
sage_root/configure
sage_root/configure.ac
sage_root/build/.gitignore
sage_root/build/README.txt
sage_root/build/setup.py
sage_root/build/tox.ini
sage_root/build/bin/sage-apply-patches
sage_root/build/bin/sage-bootstrap-python
sage_root/build/bin/sage-build-env
sage_root/build/bin/sage-build-env-config.in
sage_root/build/bin/sage-build-num-threads
sage_root/build/bin/sage-clone-source
sage_root/build/bin/sage-dist-helpers
sage_root/build/bin/sage-download-file
sage_root/build/bin/sage-flock
sage_root/build/bin/sage-get-system-packages
sage_root/build/bin/sage-guess-package-system
sage_root/build/bin/sage-logger
sage_root/build/bin/sage-package
sage_root/build/bin/sage-pip-install
sage_root/build/bin/sage-pip-uninstall
sage_root/build/bin/sage-print-system-package-command
sage_root/build/bin/sage-sdist
sage_root/build/bin/sage-site
sage_root/build/bin/sage-spkg
sage_root/build/bin/sage-spkg-info
sage_root/build/bin/sage-spkg-uninstall
sage_root/build/bin/sage-starts
sage_root/build/bin/sage-uncompress-spkg
sage_root/build/bin/sage-venv
sage_root/build/bin/testcc.sh
sage_root/build/bin/testcflags.sh
sage_root/build/bin/testcxx.sh
sage_root/build/bin/write-dockerfile.sh
sage_root/build/make/.gitignore
sage_root/build/make/Makefile-auto.am
sage_root/build/make/Makefile-auto.in
sage_root/build/make/Makefile.in
sage_root/build/make/install
sage_root/build/pkgs/4ti2/SPKG.rst
sage_root/build/pkgs/4ti2/checksums.ini
sage_root/build/pkgs/4ti2/dependencies
sage_root/build/pkgs/4ti2/package-version.txt
sage_root/build/pkgs/4ti2/spkg-check.in
sage_root/build/pkgs/4ti2/spkg-configure.m4
sage_root/build/pkgs/4ti2/spkg-install.in
sage_root/build/pkgs/4ti2/type
sage_root/build/pkgs/4ti2/distros/arch.txt
sage_root/build/pkgs/4ti2/distros/conda.txt
