Metadata-Version: 2.1
Name: sage-conf
Version: 9.5
Summary: Sage: Open Source Mathematics Software: Configuration module for the SageMath library
Home-page: https://www.sagemath.org
Author: The Sage Developers
Author-email: sage-support@googlegroups.com
License: GNU General Public License (GPL) v3 or later
Platform: UNKNOWN
